taipy/__init__.py
taipy/templates/version.json
taipy/templates/multi-page-gui/cookiecutter.json
taipy/templates/multi-page-gui/hooks/post_gen_project.py
taipy/templates/multi-page-gui/{{cookiecutter.application_name}}/requirements.txt
taipy/templates/multi-page-gui/{{cookiecutter.application_name}}/{{cookiecutter.application_main_file}}
taipy/templates/multi-page-gui/{{cookiecutter.application_name}}/pages/__init__.py
taipy/templates/multi-page-gui/{{cookiecutter.application_name}}/pages/root.md
taipy/templates/multi-page-gui/{{cookiecutter.application_name}}/pages/root.py
taipy/templates/multi-page-gui/{{cookiecutter.application_name}}/pages/page_1/__init__.py
taipy/templates/multi-page-gui/{{cookiecutter.application_name}}/pages/page_1/page_1.md
taipy/templates/multi-page-gui/{{cookiecutter.application_name}}/pages/page_1/page_1.py
taipy/templates/multi-page-gui/{{cookiecutter.application_name}}/pages/page_2/__init__.py
taipy/templates/multi-page-gui/{{cookiecutter.application_name}}/pages/page_2/page_2.md
taipy/templates/multi-page-gui/{{cookiecutter.application_name}}/pages/page_2/page_2.py
taipy/templates/taipy-default-template/cookiecutter.json
taipy/templates/taipy-default-template/hooks/post_gen_project.py
taipy/templates/taipy-default-template/{{cookiecutter.application_name}}/requirements.txt
taipy/templates/taipy-default-template/{{cookiecutter.application_name}}/{{cookiecutter.application_main_file}}
taipy/templates/taipy-default-template/{{cookiecutter.application_name}}/images/taipy_logo.jpg
taipy_templates-2.3.1.dist-info/LICENSE
taipy_templates-2.3.1.dist-info/METADATA
taipy_templates-2.3.1.dist-info/WHEEL
taipy_templates-2.3.1.dist-info/top_level.txt
taipy_templates-2.3.1.dist-info/RECORD
