Metadata-Version: 2.1
Name: taipy-templates
Version: 2.3.1
Summary: An open-source package holding Taipy application templates.
Home-page: https://github.com/avaiga/taipy-templates
Author: Avaiga
Author-email: dev@taipy.io
License: Apache License 2.0
Keywords: taipy-templates
Classifier: Intended Audience :: Developers
Classifier: License :: OSI Approved :: Apache Software License
Classifier: Natural Language :: English
Classifier: Programming Language :: Python :: 3
Classifier: Programming Language :: Python :: 3.8
Classifier: Programming Language :: Python :: 3.9
Classifier: Programming Language :: Python :: 3.10
Classifier: Programming Language :: Python :: 3.11
Requires-Python: >=3.8
License-File: LICENSE
